font_collector/__init__.py
font_collector/__main__.py
font_collector/_version.py
font_collector/collect_fonts.py
font_collector/exceptions.py
font_collector/mkvfontvalidator.py
font_collector/parse_arguments.py
font_collector/py.typed
font_collector/ass/__init__.py
font_collector/ass/abc_ass_document.py
font_collector/ass/ass_document.py
font_collector/ass/ass_style.py
font_collector/ass/usage_data.py
font_collector/font/__init__.py
font_collector/font/abc_font_face.py
font_collector/font/chinese_variant.py
font_collector/font/cmap.py
font_collector/font/factory_abc_font_face.py
font_collector/font/font_collection.py
font_collector/font/font_file.py
font_collector/font/font_loader.py
font_collector/font/font_parser.py
font_collector/font/font_result.py
font_collector/font/font_type.py
font_collector/font/lcid.py
font_collector/font/name.py
font_collector/font/normal_font_face.py
font_collector/font/variable_font_face.py
font_collector/font/weight_helper.py
font_collector/font/selection_strategy/__init__.py
font_collector/font/selection_strategy/font_selection_strategy.py
font_collector/font/selection_strategy/font_selection_strategy_libass.py
font_collector/font/selection_strategy/font_selection_strategy_vsfilter.py
font_collector/mkvtoolnix/__init__.py
font_collector/mkvtoolnix/exit_code.py
font_collector/mkvtoolnix/mkv_ass_file.py
font_collector/mkvtoolnix/mkv_font_file.py
font_collector/mkvtoolnix/mkv_utils.py
font_collector/mkvtoolnix/mkvextract.py
font_collector/mkvtoolnix/mkvmerge.py
font_collector/mkvtoolnix/mkvpropedit.py
font_collector/system_lang/__init__.py
font_collector/system_lang/abc_system_lang.py
font_collector/system_lang/linux_lang.py
font_collector/system_lang/mac_lang.py
font_collector/system_lang/system_lang.py
font_collector/system_lang/windows_lang.py
fontcollector-4.0.1.dist-info/licenses/LICENSE
fontcollector-4.0.1.dist-info/METADATA
fontcollector-4.0.1.dist-info/WHEEL
fontcollector-4.0.1.dist-info/entry_points.txt
fontcollector-4.0.1.dist-info/top_level.txt
fontcollector-4.0.1.dist-info/RECORD
