Metadata-Version: 2.4
Name: FontCollector
Version: 4.0.1
Summary: FontCollector for Advanced SubStation Alpha file.
Author-email: moi15moi <moi15moismokerlolilol@gmail.com>
License-Expression: MIT
Project-URL: Source, https://github.com/moi15moi/FontCollector/
Project-URL: Tracker, https://github.com/moi15moi/FontCollector/issues/
Classifier: Development Status :: 5 - Production/Stable
Classifier: Intended Audience :: Developers
Classifier: Intended Audience :: End Users/Desktop
Classifier: Programming Language :: Python
Classifier: Programming Language :: Python :: 3
Classifier: Programming Language :: Python :: 3.10
Classifier: Programming Language :: Python :: 3.11
Classifier: Programming Language :: Python :: 3.12
Classifier: Programming Language :: Python :: 3.13
Classifier: Programming Language :: Python :: 3.14
Classifier: Typing :: Typed
Requires-Python: >=3.10
License-File: LICENSE
Requires-Dist: ass<2,>=1.0.0
Requires-Dist: ass-tag-analyzer<1
Requires-Dist: fontTools<5,>=4.61.1
Requires-Dist: freetype-py<3,>2
Requires-Dist: FindSystemFontsFilename<1,>=0.3.3
Requires-Dist: langcodes<4,>=3.5.0
Dynamic: license-file
